[{"time":2,"mag":2.22,"place":"0 km NW of Piedmont, California","lat":37.8308333,"long":-122.239,"depth":3.53},{"time":2,"mag":2.3,"place":"1 km NW of Piedmont, California","lat":37.8306667,"long":-122.241,"depth":5.23},{"time":21,"mag":2.33,"place":"3 km SSW of Ridgemark, California","lat":36.7865,"long":-121.3855,"depth":6.27},{"time":17,"mag":2.29,"place":"4 km ESE of Aromas, California","lat":36.8645,"long":-121.5965,"depth":5.47},{"time":7,"mag":2.86,"place":"2 km NE of Pacifica, California","lat":37.6281667,"long":-122.4713333,"depth":7.67},{"time":5,"mag":2.06,"place":"6 km SSW of Monument Hills, California","lat":38.6036667,"long":-121.8946667,"depth":11.78},{"time":9,"mag":2.36,"place":"32 km SW of South Dos Palos, California","lat":36.7375,"long":-120.8868333,"depth":1.38},{"time":2,"mag":2.09,"place":"6 km S of Monument Hills, California","lat":38.6045,"long":-121.8766667,"depth":8.67},{"time":1,"mag":2.67,"place":"3 km S of Monument Hills, California","lat":38.6346667,"long":-121.8831667,"depth":15.36},{"time":1,"mag":2.95,"place":"3 km SSW of Monument Hills, California","lat":38.6355,"long":-121.8868333,"depth":15.49},{"time":23,"mag":2.35,"place":"4 km S of Monument Hills, California","lat":38.6256667,"long":-121.8851667,"depth":15},{"time":18,"mag":2.38,"place":"5 km S of Monument Hills, California","lat":38.6126667,"long":-121.8875,"depth":19.36},{"time":17,"mag":2.81,"place":"Northern California","lat":38.637,"long":-121.8883333,"depth":15.32},{"time":9,"mag":2.49,"place":"6 km S of Monument Hills, California","lat":38.6066667,"long":-121.8781667,"depth":11.5},{"time":17,"mag":2.02,"place":"11 km S of Half Moon Bay, California","lat":37.361,"long":-122.4488333,"depth":10.66},{"time":3,"mag":2.25,"place":"22 km NNE of Soledad, California","lat":36.5996667,"long":-121.2008333,"depth":2.4},{"time":17,"mag":2.15,"place":"21 km NE of Soledad, California","lat":36.5626667,"long":-121.1513333,"depth":2.65},{"time":16,"mag":2.13,"place":"6 km S of Monument Hills, California","lat":38.606,"long":-121.8728333,"depth":12.39},{"time":16,"mag":2.13,"place":"3 km E of Madison, California","lat":38.6843333,"long":-121.9311667,"depth":19.17},{"time":15,"mag":2.53,"place":"5 km SSW of Monument Hills, California","lat":38.6225,"long":-121.9056667,"depth":14.75},{"time":14,"mag":2.15,"place":"3 km SSE of Portola Valley, California","lat":37.3525,"long":-122.225,"depth":11.01},{"time":17,"mag":2.07,"place":"9 km NE of Healdsburg, California","lat":38.6613333,"long":-122.7765,"depth":2.18},{"time":6,"mag":2.2,"place":"14 km N of Morgan Hill, California","lat":37.2625,"long":-121.6465,"depth":3.95},{"time":13,"mag":2.08,"place":"6 km SE of Cottonwood, California","lat":38.6125,"long":-121.9215,"depth":19.17},{"time":14,"mag":2.15,"place":"22 km NE of Soledad, California","lat":36.5641667,"long":-121.151,"depth":2.59},{"time":0,"mag":2.34,"place":"26 km NE of Greenfield, California","lat":36.4586667,"long":-121.0033333,"depth":6.65},{"time":16,"mag":3.6,"place":"26 km NE of Greenfield, California","lat":36.4631667,"long":-121.007,"depth":6.5},{"time":18,"mag":2.89,"place":"5 km SSW of Monument Hills, California","lat":38.6201667,"long":-121.901,"depth":13.32},{"time":6,"mag":2.3,"place":"6 km SSW of Yountville, California","lat":38.3425,"long":-122.3758333,"depth":7.88},{"time":18,"mag":2.54,"place":"22 km NNE of Soledad, California","lat":36.6,"long":-121.2101667,"depth":8.46},{"time":18,"mag":2.03,"place":"3 km W of Orinda, California","lat":37.8768333,"long":-122.2221667,"depth":10.24},{"time":23,"mag":2.67,"place":"6 km SSW of Yountville, California","lat":38.3446667,"long":-122.386,"depth":7.55},{"time":4,"mag":2.17,"place":"22 km NE of Soledad, California","lat":36.5905,"long":-121.1876667,"depth":4.38},{"time":23,"mag":2.57,"place":"22 km NE of Soledad, California","lat":36.5896667,"long":-121.1866667,"depth":4.48},{"time":19,"mag":2.61,"place":"5 km WNW of San Juan Bautista, California","lat":36.8575,"long":-121.5945,"depth":7.19},{"time":12,"mag":2.69,"place":"5 km SE of Aromas, California","lat":36.8598333,"long":-121.5965,"depth":7},{"time":11,"mag":2.68,"place":"4 km WNW of San Juan Bautista, California","lat":36.859,"long":-121.5903333,"depth":6.66},{"time":11,"mag":2.84,"place":"5 km WNW of San Juan Bautista, California","lat":36.8593333,"long":-121.5948333,"depth":7.16},{"time":23,"mag":2.53,"place":"11 km NW of Davenport, California","lat":37.094,"long":-122.2718333,"depth":13.06},{"time":1,"mag":2.09,"place":"24 km NE of Greenfield, California","lat":36.4681667,"long":-121.0478333,"depth":4.51},{"time":18,"mag":2.03,"place":"7 km N of Hollister, California","lat":36.9205,"long":-121.4106667,"depth":8.48},{"time":0,"mag":2.27,"place":"7 km N of Hollister, California","lat":36.9223333,"long":-121.4118333,"depth":8.88},{"time":18,"mag":2.51,"place":"21 km NE of Soledad, California","lat":36.5731667,"long":-121.1683333,"depth":2.62},{"time":7,"mag":2.55,"place":"16 km E of Seven Trees, California","lat":37.2781667,"long":-121.6548333,"depth":6.29},{"time":7,"mag":2.27,"place":"16 km E of Seven Trees, California","lat":37.2821667,"long":-121.6498333,"depth":7.36},{"time":10,"mag":2.1,"place":"6 km S of Sunol, California","lat":37.539,"long":-121.8951667,"depth":7.62},{"time":21,"mag":2.24,"place":"7 km E of Blackhawk, California","lat":37.8286667,"long":-121.8236667,"depth":12.33},{"time":15,"mag":3.55,"place":"8 km S of Tres Pinos, California","lat":36.713,"long":-121.3113333,"depth":7.59},{"time":13,"mag":2.13,"place":"5 km S of Gilroy, California","lat":36.9553333,"long":-121.5683333,"depth":6.66},{"time":2,"mag":2.14,"place":"4 km NE of Inverness, California","lat":38.123,"long":-122.8181667,"depth":11.27},{"time":6,"mag":2.2,"place":"12 km S of Tres Pinos, California","lat":36.6818333,"long":-121.3051667,"depth":2.95},{"time":13,"mag":2.04,"place":"11 km S of Tres Pinos, California","lat":36.6888333,"long":-121.3183333,"depth":4.03},{"time":11,"mag":2.1,"place":"2 km SSW of San Juan Bautista, California","lat":36.8198333,"long":-121.5458333,"depth":5.37},{"time":1,"mag":2.67,"place":"17 km SSE of Tres Pinos, California","lat":36.6386667,"long":-121.2598333,"depth":9.31},{"time":22,"mag":2.37,"place":"8 km NNE of East Foothills, California","lat":37.4563333,"long":-121.7831667,"depth":8.78},{"time":12,"mag":2.1,"place":"9 km SSW of Calistoga, California","lat":38.4975,"long":-122.6241667,"depth":8.7},{"time":6,"mag":2.41,"place":"6 km WNW of Broadmoor, California","lat":37.7171667,"long":-122.544,"depth":10.48},{"time":7,"mag":2.2,"place":"0 km NE of North Gate, California","lat":37.9123333,"long":-121.9905,"depth":11.51},{"time":16,"mag":2.06,"place":"10 km S of Tres Pinos, California","lat":36.6986667,"long":-121.3281667,"depth":4.31},{"time":2,"mag":2.03,"place":"2 km NNE of Pacifica, California","lat":37.6295,"long":-122.474,"depth":7.54},{"time":14,"mag":2.06,"place":"9 km SSW of Tres Pinos, California","lat":36.7071667,"long":-121.3456667,"depth":2.96},{"time":2,"mag":2.8,"place":"17 km SSE of Tres Pinos, California","lat":36.6413333,"long":-121.2635,"depth":10.09},{"time":8,"mag":3.25,"place":"11 km ESE of East Foothills, California","lat":37.3363333,"long":-121.6953333,"depth":8.13},{"time":6,"mag":2.05,"place":"20 km SSE of Tres Pinos, California","lat":36.621,"long":-121.2303333,"depth":5.34},{"time":21,"mag":2.09,"place":"23 km NE of Soledad, California","lat":36.5636667,"long":-121.13,"depth":4.45},{"time":17,"mag":2.07,"place":"7 km WSW of Ridgemark, California","lat":36.781,"long":-121.4343333,"depth":9.14},{"time":17,"mag":2.07,"place":"7 km SW of Ridgemark, California","lat":36.7738333,"long":-121.4315,"depth":8.02},{"time":10,"mag":2.11,"place":"21 km NE of Soledad, California","lat":36.567,"long":-121.1583333,"depth":3.47},{"time":0,"mag":2.04,"place":"21 km NE of Soledad, California","lat":36.5688333,"long":-121.1603333,"depth":3.52},{"time":10,"mag":2.12,"place":"24 km NE of Greenfield, California","lat":36.4733333,"long":-121.0435,"depth":1.65},{"time":9,"mag":2.06,"place":"11 km ESE of East Foothills, California","lat":37.3318333,"long":-121.6993333,"depth":7.05},{"time":11,"mag":2.27,"place":"28 km ENE of Soledad, California","lat":36.5475,"long":-121.045,"depth":8.48},{"time":11,"mag":2.31,"place":"28 km ENE of Soledad, California","lat":36.547,"long":-121.0475,"depth":7.91},{"time":19,"mag":2.19,"place":"0 km WNW of Hollister, California","lat":36.8543333,"long":-121.4115,"depth":6.03},{"time":17,"mag":2.03,"place":"2 km W of Clyde, California","lat":38.0256667,"long":-122.056,"depth":7.79},{"time":0,"mag":3.54,"place":"3 km SE of Piedmont, California","lat":37.8046667,"long":-122.1975,"depth":4.02},{"time":4,"mag":2.11,"place":"4 km WSW of Saratoga, California","lat":37.2445,"long":-122.0655,"depth":1.6},{"time":15,"mag":2.1,"place":"21 km NNE of Soledad, California","lat":36.5895,"long":-121.1935,"depth":6.01},{"time":18,"mag":2.11,"place":"1 km E of Berkeley, California","lat":37.873,"long":-122.2531667,"depth":8.84},{"time":12,"mag":2.37,"place":"Central California","lat":36.7808333,"long":-121.4316667,"depth":8.88},{"time":16,"mag":2.27,"place":"21 km NE of Soledad, California","lat":36.567,"long":-121.1631667,"depth":6.15},{"time":13,"mag":2.31,"place":"24 km NE of Greenfield, California","lat":36.4678333,"long":-121.0471667,"depth":7.27},{"time":3,"mag":2.17,"place":"5 km ENE of East Foothills, California","lat":37.4001667,"long":-121.7628333,"depth":3.24},{"time":9,"mag":2.26,"place":"25 km NE of Soledad, California","lat":36.5628333,"long":-121.0935,"depth":9.25},{"time":15,"mag":2,"place":"8 km ENE of Gilroy, California","lat":37.021,"long":-121.475,"depth":7.27},{"time":13,"mag":2.22,"place":"24 km NE of Soledad, California","lat":36.5693333,"long":-121.126,"depth":8.43},{"time":7,"mag":2.11,"place":"6 km NE of East Foothills, California","lat":37.427,"long":-121.7736667,"depth":7.7},{"time":22,"mag":2.09,"place":"8 km SSE of Sunol, California","lat":37.5278333,"long":-121.8436667,"depth":3.42},{"time":1,"mag":2.13,"place":"3 km ESE of Deer Park, California","lat":38.5186667,"long":-122.437,"depth":12.48},{"time":2,"mag":2.33,"place":"1 km ENE of Ridgemark, California","lat":36.8193333,"long":-121.3511667,"depth":6.3},{"time":2,"mag":2.77,"place":"1 km ENE of Ridgemark, California","lat":36.8196667,"long":-121.3523333,"depth":6.41},{"time":19,"mag":2.76,"place":"21 km NE of Soledad, California","lat":36.5751667,"long":-121.1686667,"depth":3.96},{"time":1,"mag":2.28,"place":"26 km NE of Greenfield, California","lat":36.4636667,"long":-121.0068333,"depth":5.67},{"time":1,"mag":2.1,"place":"21 km NE of Soledad, California","lat":36.5746667,"long":-121.1716667,"depth":5.81},{"time":20,"mag":2.39,"place":"22 km ENE of Soledad, California","lat":36.5158333,"long":-121.1001667,"depth":5.39},{"time":11,"mag":2.08,"place":"21 km NE of Soledad, California","lat":36.5501667,"long":-121.137,"depth":2.9},{"time":1,"mag":2,"place":"1 km E of Angwin, California","lat":38.5748333,"long":-122.4361667,"depth":9.14},{"time":15,"mag":3.19,"place":"10 km S of Tres Pinos, California","lat":36.6943333,"long":-121.3271667,"depth":3.62},{"time":14,"mag":3.07,"place":"10 km S of Tres Pinos, California","lat":36.6945,"long":-121.3365,"depth":4.45},{"time":14,"mag":2.45,"place":"10 km S of Tres Pinos, California","lat":36.6996667,"long":-121.332,"depth":3.32},{"time":9,"mag":3.62,"place":"9 km S of Tres Pinos, California","lat":36.7015,"long":-121.338,"depth":4.4},{"time":13,"mag":2.26,"place":"3 km N of Hollister, California","lat":36.8873333,"long":-121.401,"depth":9.03},{"time":3,"mag":2.59,"place":"2 km S of Diablo, California","lat":37.8095,"long":-121.953,"depth":9.65},{"time":17,"mag":2,"place":"0 km WSW of Muir Beach, California","lat":37.8585,"long":-122.5893333,"depth":3.32},{"time":2,"mag":3.41,"place":"21 km NE of Soledad, California","lat":36.5765,"long":-121.1765,"depth":7.78},{"time":22,"mag":2.08,"place":"7 km ENE of Gilroy, California","lat":37.0281667,"long":-121.4911667,"depth":3.68},{"time":19,"mag":2.04,"place":"1 km NE of Pacifica, California","lat":37.6273333,"long":-122.4728333,"depth":7.63},{"time":23,"mag":2.05,"place":"9 km S of Tres Pinos, California","lat":36.701,"long":-121.3356667,"depth":4.8},{"time":19,"mag":2.32,"place":"19 km W of Volta, California","lat":37.1198333,"long":-121.1431667,"depth":0.19},{"time":7,"mag":2.13,"place":"21 km NE of Soledad, California","lat":36.5781667,"long":-121.1721667,"depth":3.34},{"time":12,"mag":2.09,"place":"11 km SE of Sunol, California","lat":37.5105,"long":-121.8053333,"depth":7.84},{"time":17,"mag":2.94,"place":"3 km SW of American Canyon, California","lat":38.153,"long":-122.2905,"depth":10.44},{"time":16,"mag":3.16,"place":"4 km NE of Kenwood, California","lat":38.4408333,"long":-122.5056667,"depth":10.91},{"time":12,"mag":2.13,"place":"23 km ENE of Soledad, California","lat":36.4963333,"long":-121.0745,"depth":3.22},{"time":10,"mag":2.18,"place":"3 km E of Saint Helena, California","lat":38.5088333,"long":-122.4325,"depth":12.6},{"time":4,"mag":2.54,"place":"7 km SW of Moskowite Corner, California","lat":38.4051667,"long":-122.2561667,"depth":6.74},{"time":2,"mag":2.19,"place":"9 km NNE of East Foothills, California","lat":37.4555,"long":-121.7728333,"depth":6.25},{"time":21,"mag":2.14,"place":"21 km NE of Soledad, California","lat":36.5815,"long":-121.1793333,"depth":4.39},{"time":5,"mag":2.68,"place":"3 km NNW of Benicia, California","lat":38.0786667,"long":-122.1698333,"depth":9.44},{"time":17,"mag":2.16,"place":"11 km S of Tres Pinos, California","lat":36.6876667,"long":-121.318,"depth":4.92},{"time":6,"mag":2.09,"place":"16 km SSE of Tres Pinos, California","lat":36.646,"long":-121.2611667,"depth":5.37},{"time":20,"mag":2.35,"place":"3 km E of Saint Helena, California","lat":38.4993333,"long":-122.428,"depth":10.2},{"time":15,"mag":2.13,"place":"23 km NE of Greenfield, California","lat":36.4683333,"long":-121.0485,"depth":5.31},{"time":8,"mag":2.07,"place":"9 km E of Gilroy, California","lat":37.0013333,"long":-121.4576667,"depth":7.66},{"time":16,"mag":2.96,"place":"18 km SSE of Tres Pinos, California","lat":36.631,"long":-121.25,"depth":9.55},{"time":14,"mag":2.88,"place":"13 km SSE of Tres Pinos, California","lat":36.6688333,"long":-121.2858333,"depth":2.92},{"time":11,"mag":2.35,"place":"10 km S of Tres Pinos, California","lat":36.6955,"long":-121.3251667,"depth":5.48},{"time":6,"mag":2.02,"place":"10 km S of Tres Pinos, California","lat":36.6921667,"long":-121.3231667,"depth":3.79},{"time":0,"mag":2.23,"place":"2 km SW of San Juan Bautista, California","lat":36.8313333,"long":-121.563,"depth":5.25},{"time":0,"mag":2.93,"place":"2 km WSW of San Juan Bautista, California","lat":36.833,"long":-121.5643333,"depth":5.58},{"time":22,"mag":2.87,"place":"10 km S of Tres Pinos, California","lat":36.6911667,"long":-121.316,"depth":3.6},{"time":17,"mag":2.06,"place":"10 km S of Tres Pinos, California","lat":36.6938333,"long":-121.3245,"depth":3.97},{"time":16,"mag":2.27,"place":"Central California","lat":36.6938333,"long":-121.324,"depth":3.9},{"time":14,"mag":2.94,"place":"11 km S of Tres Pinos, California","lat":36.6895,"long":-121.3215,"depth":5.58},{"time":14,"mag":3.93,"place":"10 km S of Tres Pinos, California","lat":36.697,"long":-121.3413333,"depth":4.24},{"time":14,"mag":4.22,"place":"10 km S of Tres Pinos, California","lat":36.6925,"long":-121.3296667,"depth":5.87},{"time":6,"mag":2.11,"place":"7 km WSW of Gilroy, California","lat":36.9823333,"long":-121.6423333,"depth":5.46},{"time":5,"mag":3.07,"place":"25 km WSW of Volta, California","lat":37.028,"long":-121.202,"depth":0.2},{"time":0,"mag":2.03,"place":"17 km NE of San Martin, California","lat":37.1918333,"long":-121.4638333,"depth":5.81},{"time":18,"mag":2.2,"place":"3 km NNW of Hollister, California","lat":36.8808333,"long":-121.4131667,"depth":8.83},{"time":2,"mag":3.68,"place":"25 km WSW of Volta, California","lat":37.0295,"long":-121.1981667,"depth":2.02},{"time":23,"mag":2.77,"place":"10 km S of Tres Pinos, California","lat":36.6936667,"long":-121.3261667,"depth":4.33},{"time":23,"mag":2.89,"place":"11 km SSW of Tres Pinos, California","lat":36.693,"long":-121.3495,"depth":4.92},{"time":23,"mag":3.28,"place":"11 km S of Tres Pinos, California","lat":36.6855,"long":-121.333,"depth":4.43},{"time":23,"mag":2.33,"place":"10 km S of Tres Pinos, California","lat":36.6926667,"long":-121.3291667,"depth":4.47},{"time":23,"mag":2.85,"place":"10 km S of Tres Pinos, California","lat":36.6948333,"long":-121.3256667,"depth":4.85},{"time":23,"mag":2.74,"place":"10 km S of Tres Pinos, California","lat":36.6936667,"long":-121.3246667,"depth":4.12},{"time":23,"mag":3.34,"place":"10 km S of Tres Pinos, California","lat":36.6971667,"long":-121.331,"depth":4.45},{"time":22,"mag":2.05,"place":"11 km S of Tres Pinos, California","lat":36.6903333,"long":-121.3211667,"depth":4.26},{"time":22,"mag":3.84,"place":"11 km S of Tres Pinos, California","lat":36.6898333,"long":-121.3251667,"depth":4.91},{"time":22,"mag":2.33,"place":"10 km S of Tres Pinos, California","lat":36.6933333,"long":-121.3246667,"depth":3.76},{"time":22,"mag":2.35,"place":"10 km S of Tres Pinos, California","lat":36.6941667,"long":-121.3251667,"depth":3.91},{"time":22,"mag":3.12,"place":"11 km S of Tres Pinos, California","lat":36.6908333,"long":-121.3201667,"depth":4.07},{"time":23,"mag":2.25,"place":"9 km E of Gilroy, California","lat":37.0026667,"long":-121.4638333,"depth":3.58},{"time":1,"mag":2.26,"place":"21 km SSE of Tres Pinos, California","lat":36.6108333,"long":-121.22,"depth":5.31},{"time":0,"mag":2.3,"place":"25 km ENE of Greenfield, California","lat":36.447,"long":-121.0048333,"depth":8.56},{"time":16,"mag":2.95,"place":"1 km W of Green Valley, California","lat":38.2548333,"long":-122.1806667,"depth":9.73},{"time":12,"mag":2.62,"place":"5 km SSW of Muir Beach, California","lat":37.8176667,"long":-122.5963333,"depth":5.39},{"time":21,"mag":2.07,"place":"6 km WNW of Diablo Grande, California","lat":37.4125,"long":-121.3521667,"depth":4.47},{"time":10,"mag":2.21,"place":"5 km NW of American Canyon, California","lat":38.2028333,"long":-122.31,"depth":8.63},{"time":2,"mag":2.04,"place":"0 km S of Concord, California","lat":37.973,"long":-122.0315,"depth":12.93},{"time":1,"mag":2.09,"place":"0 km SSW of Concord, California","lat":37.9711667,"long":-122.0331667,"depth":12.99},{"time":20,"mag":2.35,"place":"6 km E of Milpitas, California","lat":37.4346667,"long":-121.8391667,"depth":5.12},{"time":6,"mag":2.31,"place":"11 km SSE of Tres Pinos, California","lat":36.6878333,"long":-121.2873333,"depth":4.28},{"time":5,"mag":2.91,"place":"25 km NE of Soledad, California","lat":36.586,"long":-121.1276667,"depth":8.48},{"time":7,"mag":2.32,"place":"4 km S of San Juan Bautista, California","lat":36.8066667,"long":-121.5346667,"depth":6.18},{"time":18,"mag":2.06,"place":"15 km NNE of Angwin, California","lat":38.7061667,"long":-122.397,"depth":10.56},{"time":11,"mag":3.01,"place":"18 km SSE of Tres Pinos, California","lat":36.6343333,"long":-121.256,"depth":9.35},{"time":8,"mag":2.56,"place":"25 km WSW of Volta, California","lat":37.0305,"long":-121.1961667,"depth":0.97},{"time":7,"mag":2.04,"place":"1 km N of Piedmont, California","lat":37.839,"long":-122.2296667,"depth":4.91},{"time":21,"mag":2.46,"place":"6 km WSW of Gilroy, California","lat":36.982,"long":-121.6381667,"depth":3.27},{"time":16,"mag":2.08,"place":"21 km NE of Soledad, California","lat":36.5455,"long":-121.1355,"depth":5.19},{"time":6,"mag":2.14,"place":"24 km NE of Greenfield, California","lat":36.4458333,"long":-121.0156667,"depth":1.76},{"time":3,"mag":2.44,"place":"1 km SSE of Pacheco, California","lat":37.9708333,"long":-122.069,"depth":15.82},{"time":13,"mag":2.64,"place":"7 km W of Saint Helena, California","lat":38.493,"long":-122.5601667,"depth":9.59},{"time":19,"mag":2.45,"place":"9 km SSW of Ridgemark, California","lat":36.7346667,"long":-121.4115,"depth":6.19},{"time":6,"mag":3.35,"place":"9 km NNW of Boulder Creek, California","lat":37.2076667,"long":-122.1655,"depth":12.99},{"time":12,"mag":2.13,"place":"22 km NE of Soledad, California","lat":36.5796667,"long":-121.1696667,"depth":3.27}]