[{"time":5,"mag":2.14,"place":"5 km SSE of San Juan Bautista, California","lat":36.801,"long":-121.5123333,"depth":3.566},{"time":2,"mag":2.94,"place":"Central California","lat":36.6118333,"long":-121.2183333,"depth":6.049},{"time":21,"mag":2.43,"place":"21 km SSE of Tres Pinos, California","lat":36.613,"long":-121.2191667,"depth":5.909},{"time":2,"mag":2.29,"place":"23 km NE of Greenfield, California","lat":36.4651667,"long":-121.0446667,"depth":5.129},{"time":23,"mag":2.04,"place":"20 km SSE of Tres Pinos, California","lat":36.617,"long":-121.2258333,"depth":4.994},{"time":10,"mag":2.6,"place":"3 km N of Fremont, California","lat":37.5808333,"long":-121.9808333,"depth":8.18},{"time":8,"mag":2.23,"place":"21 km SSE of Tres Pinos, California","lat":36.6138333,"long":-121.2196667,"depth":4.551},{"time":7,"mag":2.38,"place":"21 km SSE of Tres Pinos, California","lat":36.6123333,"long":-121.2176667,"depth":5.081},{"time":7,"mag":3.33,"place":"21 km SSE of Tres Pinos, California","lat":36.6156667,"long":-121.2233333,"depth":5.75},{"time":7,"mag":2.23,"place":"19 km NNE of Soledad, California","lat":36.5833333,"long":-121.2285,"depth":9.104},{"time":10,"mag":2.53,"place":"24 km NE of Greenfield, California","lat":36.4651667,"long":-121.0443333,"depth":5.571},{"time":3,"mag":2.43,"place":"11 km N of Pittsburg, California","lat":38.1336667,"long":-121.8935,"depth":19.943},{"time":19,"mag":2.28,"place":"21 km SSE of Tres Pinos, California","lat":36.6161667,"long":-121.2238333,"depth":6.264},{"time":19,"mag":3.18,"place":"21 km SSE of Tres Pinos, California","lat":36.6161667,"long":-121.2243333,"depth":6.43},{"time":19,"mag":2.23,"place":"22 km NE of Soledad, California","lat":36.5401667,"long":-121.125,"depth":3.155},{"time":12,"mag":2.42,"place":"24 km ENE of Soledad, California","lat":36.489,"long":-121.0658333,"depth":0.865},{"time":20,"mag":2.02,"place":"2 km S of Pittsburg, California","lat":38.0025,"long":-121.8815,"depth":17.084},{"time":2,"mag":2.15,"place":"30 km ENE of Soledad, California","lat":36.5751667,"long":-121.0371667,"depth":7.331},{"time":0,"mag":2.38,"place":"21 km NNE of Soledad, California","lat":36.5951667,"long":-121.2048333,"depth":8.361},{"time":12,"mag":2.15,"place":"12 km S of Tres Pinos, California","lat":36.6755,"long":-121.304,"depth":5.669},{"time":7,"mag":2.02,"place":"13 km SE of Tres Pinos, California","lat":36.7036667,"long":-121.2075,"depth":4.897},{"time":7,"mag":2.01,"place":"0 km SW of Tres Pinos, California","lat":36.7848333,"long":-121.3285,"depth":7.714},{"time":2,"mag":2.06,"place":"8 km SSE of Monument Hills, California","lat":38.5911667,"long":-121.854,"depth":15.307},{"time":1,"mag":2.1,"place":"4 km E of Healdsburg, California","lat":38.6085,"long":-122.8171667,"depth":5.321},{"time":23,"mag":2.24,"place":"13 km ENE of Hollister, California","lat":36.9068333,"long":-121.2698333,"depth":6.86},{"time":9,"mag":2.22,"place":"4 km N of Hollister, California","lat":36.8948333,"long":-121.406,"depth":9.286},{"time":11,"mag":2.32,"place":"3 km SSW of San Juan Bautista, California","lat":36.8193333,"long":-121.5493333,"depth":5.275},{"time":7,"mag":2.13,"place":"4 km S of San Juan Bautista, California","lat":36.808,"long":-121.54,"depth":5.023},{"time":7,"mag":2.69,"place":"3 km S of San Juan Bautista, California","lat":36.8123333,"long":-121.5436667,"depth":5.683},{"time":11,"mag":2.83,"place":"3 km SSW of San Juan Bautista, California","lat":36.8156667,"long":-121.5505,"depth":5.681},{"time":7,"mag":3.33,"place":"3 km SSW of San Juan Bautista, California","lat":36.8146667,"long":-121.5473333,"depth":5.904},{"time":23,"mag":2.25,"place":"9 km E of San Martin, California","lat":37.0931667,"long":-121.5063333,"depth":8.43},{"time":10,"mag":2.33,"place":"25 km NE of Greenfield, California","lat":36.4668333,"long":-121.0281667,"depth":8.389},{"time":7,"mag":2.34,"place":"20 km ESE of Tres Pinos, California","lat":36.7503333,"long":-121.0985,"depth":6.633},{"time":2,"mag":3.22,"place":"9 km E of San Martin, California","lat":37.0883333,"long":-121.503,"depth":7.56},{"time":1,"mag":2.91,"place":"22 km NNE of Soledad, California","lat":36.6036667,"long":-121.2118333,"depth":8.25},{"time":23,"mag":2.72,"place":"24 km NE of Greenfield, California","lat":36.4595,"long":-121.0378333,"depth":5.931},{"time":21,"mag":2.39,"place":"21 km NNE of Soledad, California","lat":36.592,"long":-121.199,"depth":7.296},{"time":21,"mag":3.94,"place":"21 km NNE of Soledad, California","lat":36.5915,"long":-121.2008333,"depth":8.347},{"time":19,"mag":2.08,"place":"5 km ESE of Tracy, California","lat":37.7266667,"long":-121.3621667,"depth":8.049},{"time":17,"mag":2.12,"place":"6 km ESE of Tracy, California","lat":37.7215,"long":-121.3556667,"depth":8.152},{"time":15,"mag":2.6,"place":"Northern California","lat":37.7335,"long":-121.3648333,"depth":8.835},{"time":14,"mag":2.27,"place":"21 km NE of Soledad, California","lat":36.5818333,"long":-121.177,"depth":4.171},{"time":22,"mag":2.08,"place":"4 km ESE of Santa Rosa, California","lat":38.4183333,"long":-122.6683333,"depth":9.991},{"time":18,"mag":2.19,"place":"9 km SSW of Ridgemark, California","lat":36.7408333,"long":-121.4186667,"depth":6.636},{"time":0,"mag":2.09,"place":"3 km SE of Hayward, California","lat":37.6423333,"long":-122.051,"depth":2.685},{"time":20,"mag":2.37,"place":"1 km ESE of Berkeley, California","lat":37.864,"long":-122.2548333,"depth":6.842},{"time":2,"mag":2.09,"place":"7 km E of East Foothills, California","lat":37.3778333,"long":-121.729,"depth":9.25},{"time":11,"mag":2.02,"place":"24 km NE of Greenfield, California","lat":36.4666667,"long":-121.0355,"depth":5.309},{"time":10,"mag":3.41,"place":"24 km NE of Greenfield, California","lat":36.4671667,"long":-121.0351667,"depth":7.921},{"time":10,"mag":2.34,"place":"0 km SE of Hayward, California","lat":37.6645,"long":-122.074,"depth":4.979},{"time":4,"mag":2.53,"place":"24 km NE of Greenfield, California","lat":36.4651667,"long":-121.0346667,"depth":4.459},{"time":1,"mag":2.12,"place":"6 km NE of Ridgemark, California","lat":36.8525,"long":-121.3148333,"depth":7.181},{"time":22,"mag":2.04,"place":"21 km NE of Soledad, California","lat":36.5535,"long":-121.1486667,"depth":7.009},{"time":17,"mag":2.11,"place":"23 km ENE of Soledad, California","lat":36.4968333,"long":-121.0756667,"depth":2.929},{"time":14,"mag":2.05,"place":"21 km NE of Soledad, California","lat":36.576,"long":-121.1735,"depth":2.961},{"time":22,"mag":2.45,"place":"6 km NE of Ridgemark, California","lat":36.8525,"long":-121.3136667,"depth":7.021},{"time":9,"mag":2.47,"place":"6 km NE of Ridgemark, California","lat":36.8535,"long":-121.315,"depth":7.131},{"time":4,"mag":2.02,"place":"2 km W of Glen Ellen, California","lat":38.36,"long":-122.5546667,"depth":4.934},{"time":7,"mag":2.14,"place":"1 km WSW of Blackhawk, California","lat":37.816,"long":-121.9206667,"depth":5.048},{"time":7,"mag":2.39,"place":"10 km S of Muir Beach, California","lat":37.768,"long":-122.5941667,"depth":4.879},{"time":19,"mag":2.49,"place":"22 km NE of Soledad, California","lat":36.5866667,"long":-121.1825,"depth":2.653},{"time":14,"mag":2.1,"place":"4 km SSW of Green Valley, California","lat":38.219,"long":-122.1831667,"depth":5.379},{"time":17,"mag":3.05,"place":"22 km NE of Soledad, California","lat":36.586,"long":-121.1823333,"depth":3.042},{"time":9,"mag":3.25,"place":"2 km SSW of Green Valley, California","lat":38.2353333,"long":-122.1671667,"depth":9.389},{"time":11,"mag":2.03,"place":"23 km ENE of Soledad, California","lat":36.498,"long":-121.0766667,"depth":4.689},{"time":13,"mag":2.6,"place":"12 km ESE of Angwin, California","lat":38.534,"long":-122.321,"depth":4.932},{"time":3,"mag":2.19,"place":"2 km NNE of Ashland, California","lat":37.7128333,"long":-122.103,"depth":11.486},{"time":9,"mag":2.69,"place":"2 km SE of Berkeley, California","lat":37.8525,"long":-122.2486667,"depth":6.678},{"time":9,"mag":2.3,"place":"2 km SE of Berkeley, California","lat":37.8523333,"long":-122.2501667,"depth":6.799},{"time":0,"mag":2.13,"place":"71 km WSW of Davenport, California","lat":36.6628333,"long":-122.8695,"depth":5.43},{"time":6,"mag":2.32,"place":"5 km NNW of Aromas, California","lat":36.9325,"long":-121.666,"depth":7.365},{"time":1,"mag":2.41,"place":"1 km NW of Hollister, California","lat":36.8605,"long":-121.4148333,"depth":6.397},{"time":22,"mag":2.21,"place":"3 km SE of Berkeley, California","lat":37.8528333,"long":-122.2473333,"depth":6.838},{"time":11,"mag":2.23,"place":"5 km NNW of Aromas, California","lat":36.9298333,"long":-121.6666667,"depth":7.315},{"time":16,"mag":2.33,"place":"24 km NE of Greenfield, California","lat":36.478,"long":-121.0578333,"depth":7.127},{"time":14,"mag":2.8,"place":"37 km ESE of Tres Pinos, California","lat":36.6436667,"long":-120.9488333,"depth":8.953},{"time":0,"mag":2.09,"place":"6 km NE of East Foothills, California","lat":37.4315,"long":-121.7728333,"depth":9.411},{"time":16,"mag":2.09,"place":"6 km NNE of Tres Pinos, California","lat":36.8463333,"long":-121.3018333,"depth":7.335},{"time":4,"mag":2.32,"place":"17 km SSE of Tres Pinos, California","lat":36.644,"long":-121.256,"depth":2.746},{"time":9,"mag":2.04,"place":"5 km W of Moskowite Corner, California","lat":38.4476667,"long":-122.2533333,"depth":6.343},{"time":16,"mag":2.22,"place":"5 km NW of Loma Mar, California","lat":37.3033333,"long":-122.3585,"depth":8.83},{"time":3,"mag":2.07,"place":"20 km SSE of Tres Pinos, California","lat":36.6208333,"long":-121.2296667,"depth":5.216},{"time":3,"mag":2.45,"place":"14 km SSE of Tres Pinos, California","lat":36.6656667,"long":-121.2646667,"depth":4.856},{"time":3,"mag":2.53,"place":"14 km SSE of Tres Pinos, California","lat":36.6661667,"long":-121.2665,"depth":5.966},{"time":10,"mag":2.06,"place":"12 km S of Tres Pinos, California","lat":36.6746667,"long":-121.3018333,"depth":5.439},{"time":23,"mag":2.28,"place":"21 km NE of Soledad, California","lat":36.5825,"long":-121.1785,"depth":4.263},{"time":22,"mag":2.27,"place":"22 km NNE of Soledad, California","lat":36.6046667,"long":-121.2175,"depth":9.256},{"time":13,"mag":2,"place":"24 km ENE of Greenfield, California","lat":36.4355,"long":-121.0148333,"depth":5.796},{"time":6,"mag":2.57,"place":"3 km NNW of Hollister, California","lat":36.8821667,"long":-121.413,"depth":8.912},{"time":18,"mag":2.05,"place":"1 km ENE of Berkeley, California","lat":37.875,"long":-122.2538333,"depth":8.879},{"time":23,"mag":2.52,"place":"5 km W of Moskowite Corner, California","lat":38.4371667,"long":-122.2538333,"depth":11.634},{"time":23,"mag":2.25,"place":"10 km NNW of Boulder Creek, California","lat":37.2125,"long":-122.1591667,"depth":9.495},{"time":6,"mag":2.18,"place":"3 km ENE of Saint Helena, California","lat":38.5176667,"long":-122.437,"depth":10.026},{"time":10,"mag":2.02,"place":"4 km NE of Penngrove, California","lat":38.3238333,"long":-122.6273333,"depth":5.33},{"time":9,"mag":2.37,"place":"4 km NE of Penngrove, California","lat":38.3238333,"long":-122.6225,"depth":6.917},{"time":22,"mag":2.09,"place":"4 km SSE of Pittsburg, California","lat":37.9941667,"long":-121.8668333,"depth":18.225},{"time":10,"mag":2.01,"place":"6 km WSW of Moskowite Corner, California","lat":38.4181667,"long":-122.2528333,"depth":5.998},{"time":4,"mag":2.17,"place":"17 km SSE of Tres Pinos, California","lat":36.6441667,"long":-121.26,"depth":5.176},{"time":21,"mag":2.23,"place":"24 km NE of Soledad, California","lat":36.5568333,"long":-121.1081667,"depth":9.489},{"time":18,"mag":2.6,"place":"3 km SW of San Juan Bautista, California","lat":36.8235,"long":-121.5646667,"depth":6.554},{"time":17,"mag":2.38,"place":"21 km NE of Soledad, California","lat":36.5836667,"long":-121.1796667,"depth":4.343},{"time":15,"mag":2.13,"place":"24 km ENE of Soledad, California","lat":36.4981667,"long":-121.0741667,"depth":3.217},{"time":12,"mag":2.14,"place":"21 km NE of Soledad, California","lat":36.5448333,"long":-121.1351667,"depth":5.459},{"time":2,"mag":2.25,"place":"9 km SW of Brentwood, California","lat":37.8641667,"long":-121.7681667,"depth":20.808},{"time":0,"mag":2.4,"place":"22 km NE of Soledad, California","lat":36.5861667,"long":-121.1833333,"depth":4.583},{"time":6,"mag":2.17,"place":"7 km SE of Cambrian Park, California","lat":37.213,"long":-121.8706667,"depth":9.963},{"time":19,"mag":2.26,"place":"16 km WNW of Diablo Grande, California","lat":37.4645,"long":-121.4461667,"depth":3.685},{"time":11,"mag":2.05,"place":"6 km NE of East Foothills, California","lat":37.4303333,"long":-121.771,"depth":10.041},{"time":8,"mag":2.69,"place":"6 km NE of East Foothills, California","lat":37.4331667,"long":-121.7733333,"depth":11.621},{"time":23,"mag":2.37,"place":"22 km ENE of Soledad, California","lat":36.511,"long":-121.0961667,"depth":4.947},{"time":14,"mag":2.31,"place":"4 km NE of Interlaken, California","lat":36.9786667,"long":-121.6975,"depth":7.195},{"time":6,"mag":2.1,"place":"2 km NNE of San Juan Bautista, California","lat":36.8711667,"long":-121.5298333,"depth":6.94},{"time":16,"mag":2.37,"place":"2 km SW of Alamo, California","lat":37.8326667,"long":-122.0478333,"depth":9.249},{"time":13,"mag":2.32,"place":"3 km NE of Pleasanton, California","lat":37.6858333,"long":-121.8436667,"depth":12.146},{"time":12,"mag":2.24,"place":"2 km SW of San Juan Bautista, California","lat":36.8283333,"long":-121.5568333,"depth":3.895},{"time":11,"mag":2.55,"place":"2 km SSW of San Juan Bautista, California","lat":36.8233333,"long":-121.5553333,"depth":3.385},{"time":11,"mag":2.47,"place":"2 km SSW of San Juan Bautista, California","lat":36.8213333,"long":-121.548,"depth":3.685},{"time":7,"mag":2.19,"place":"Northern California","lat":37.8403333,"long":-121.947,"depth":16.22},{"time":7,"mag":2.65,"place":"8 km ENE of San Martin, California","lat":37.1166667,"long":-121.5236667,"depth":6.617},{"time":20,"mag":2.54,"place":"2 km SE of Berkeley, California","lat":37.8556667,"long":-122.2456667,"depth":8.68},{"time":18,"mag":2.7,"place":"10 km NNW of Hollister, California","lat":36.945,"long":-121.441,"depth":2.413},{"time":22,"mag":2.3,"place":"2 km N of Montara, California","lat":37.563,"long":-122.519,"depth":8.749},{"time":22,"mag":2.74,"place":"3 km N of Montara, California","lat":37.5713333,"long":-122.5111667,"depth":8.951},{"time":19,"mag":2.46,"place":"2 km N of Montara, California","lat":37.5625,"long":-122.514,"depth":8.619},{"time":19,"mag":2.62,"place":"2 km NNE of Montara, California","lat":37.5676667,"long":-122.5085,"depth":8.319},{"time":19,"mag":2.31,"place":"2 km N of Montara, California","lat":37.564,"long":-122.5121667,"depth":9.069},{"time":19,"mag":2.77,"place":"2 km NNE of Montara, California","lat":37.5623333,"long":-122.5078333,"depth":8.939},{"time":21,"mag":2.01,"place":"2 km N of Montara, California","lat":37.5608333,"long":-122.5121667,"depth":8.849},{"time":18,"mag":2.18,"place":"8 km N of East Foothills, California","lat":37.456,"long":-121.808,"depth":6.953},{"time":1,"mag":2.21,"place":"2 km SSE of Kenwood, California","lat":38.3913333,"long":-122.5288333,"depth":4.858},{"time":22,"mag":2.5,"place":"4 km SE of Pacifica, California","lat":37.5881667,"long":-122.4523333,"depth":14.429},{"time":13,"mag":2.56,"place":"30 km NE of Soledad, California","lat":36.5843333,"long":-121.0456667,"depth":7.549},{"time":16,"mag":2.1,"place":"1 km ENE of Deer Park, California","lat":38.5366667,"long":-122.4565,"depth":9.738},{"time":9,"mag":2.12,"place":"0 km N of El Cerrito, California","lat":37.9235,"long":-122.3131667,"depth":3.1},{"time":1,"mag":3.28,"place":"14 km N of Morgan Hill, California","lat":37.2633333,"long":-121.6371667,"depth":7.352},{"time":20,"mag":2.97,"place":"7 km SSE of Gilroy, California","lat":36.9396667,"long":-121.5396667,"depth":7.453},{"time":16,"mag":2.36,"place":"Central California","lat":36.5938333,"long":-121.203,"depth":7.283},{"time":5,"mag":2.56,"place":"1 km ESE of Aromas, California","lat":36.8821667,"long":-121.6255,"depth":7.035},{"time":12,"mag":2.72,"place":"5 km S of Loyola, California","lat":37.303,"long":-122.1123333,"depth":8.038},{"time":14,"mag":2.13,"place":"22 km NE of Soledad, California","lat":36.5533333,"long":-121.1285,"depth":4.319},{"time":6,"mag":2.16,"place":"24 km NE of Soledad, California","lat":36.5698333,"long":-121.1205,"depth":4.279},{"time":6,"mag":2.31,"place":"2 km ENE of Hood, California","lat":38.3788333,"long":-121.49,"depth":27.031},{"time":15,"mag":2.19,"place":"6 km SE of Rodeo, California","lat":37.9926667,"long":-122.2205,"depth":8.555},{"time":14,"mag":2.4,"place":"5 km SE of Aromas, California","lat":36.8621667,"long":-121.597,"depth":5.642},{"time":7,"mag":2.47,"place":"2 km ENE of Saint Helena, California","lat":38.516,"long":-122.4443333,"depth":10.888},{"time":16,"mag":2.2,"place":"22 km NE of Soledad, California","lat":36.5498333,"long":-121.1265,"depth":4.249},{"time":12,"mag":2.23,"place":"30 km ENE of Soledad, California","lat":36.5685,"long":-121.0376667,"depth":6.999},{"time":13,"mag":2.03,"place":"12 km SSE of Tres Pinos, California","lat":36.6771667,"long":-121.2888333,"depth":10.939},{"time":20,"mag":2.1,"place":"5 km SW of Gilroy, California","lat":36.9631667,"long":-121.6048333,"depth":5.174},{"time":9,"mag":2.36,"place":"18 km SSE of Tres Pinos, California","lat":36.6336667,"long":-121.2506667,"depth":4.406},{"time":4,"mag":2.8,"place":"37 km SW of Bolinas, California","lat":37.6863333,"long":-123.0001667,"depth":6.85},{"time":2,"mag":2,"place":"4 km NNE of Blackhawk, California","lat":37.858,"long":-121.8923333,"depth":8.249},{"time":12,"mag":2.55,"place":"25 km NE of Soledad, California","lat":36.593,"long":-121.1278333,"depth":11.063},{"time":10,"mag":3.52,"place":"14 km N of Morgan Hill, California","lat":37.2613333,"long":-121.6356667,"depth":8.085}]