[{"time":16,"mag":2,"place":"40 km ENE of Soledad, California","lat":36.584,"long":-120.9233333,"depth":8.357},{"time":15,"mag":2.06,"place":"4 km S of San Juan Bautista, California","lat":36.8071667,"long":-121.5301667,"depth":6.87},{"time":7,"mag":2.36,"place":"7 km WSW of Cobb, California","lat":38.8038333,"long":-122.8056667,"depth":0.241},{"time":2,"mag":2.92,"place":"4 km S of Cobb, California","lat":38.7795,"long":-122.7243333,"depth":1.404},{"time":15,"mag":2.23,"place":"4 km SSE of San Juan Bautista, California","lat":36.8041667,"long":-121.5255,"depth":6.88},{"time":12,"mag":2.11,"place":"7 km WSW of Cobb, California","lat":38.8035,"long":-122.8005,"depth":1.031},{"time":7,"mag":2.27,"place":"6 km W of Cobb, California","lat":38.8256667,"long":-122.8001667,"depth":3.34},{"time":6,"mag":2.01,"place":"5 km SSE of San Juan Bautista, California","lat":36.799,"long":-121.521,"depth":6.87},{"time":5,"mag":2.61,"place":"5 km SSE of San Juan Bautista, California","lat":36.8005,"long":-121.5213333,"depth":7.06},{"time":5,"mag":2.96,"place":"4 km SSE of San Juan Bautista, California","lat":36.8033333,"long":-121.5241667,"depth":7.05},{"time":21,"mag":2.91,"place":"4 km S of San Juan Bautista, California","lat":36.8071667,"long":-121.5303333,"depth":6.94},{"time":1,"mag":2.39,"place":"18 km ENE of Gilroy, California","lat":37.0961667,"long":-121.3921667,"depth":22.986},{"time":21,"mag":2.35,"place":"4 km S of San Juan Bautista, California","lat":36.8091667,"long":-121.533,"depth":6.95},{"time":19,"mag":2.28,"place":"4 km S of San Juan Bautista, California","lat":36.806,"long":-121.536,"depth":8.48},{"time":14,"mag":2,"place":"4 km S of San Juan Bautista, California","lat":36.805,"long":-121.528,"depth":6.69},{"time":13,"mag":4.3,"place":"3 km S of San Juan Bautista, California","lat":36.8111667,"long":-121.5411667,"depth":7.85},{"time":10,"mag":2.23,"place":"28 km ESE of Tres Pinos, California","lat":36.71,"long":-121.014,"depth":0.087},{"time":9,"mag":3.07,"place":"6 km W of Cobb, California","lat":38.8253333,"long":-122.8031667,"depth":2.99},{"time":1,"mag":2.08,"place":"8 km ENE of Blackhawk, California","lat":37.8608333,"long":-121.827,"depth":14.347},{"time":18,"mag":3.16,"place":"7 km W of Cobb, California","lat":38.8136667,"long":-122.8131667,"depth":2.9},{"time":5,"mag":2.54,"place":"0 km ENE of Day Valley, California","lat":37.037,"long":-121.8558333,"depth":12.547},{"time":2,"mag":2.05,"place":"7 km S of Cobb, California","lat":38.7535,"long":-122.7065,"depth":1.468},{"time":12,"mag":2.11,"place":"3 km E of Aromas, California","lat":36.8923333,"long":-121.607,"depth":2.121},{"time":19,"mag":2.24,"place":"7 km WSW of Cobb, California","lat":38.7896667,"long":-122.8043333,"depth":3.578},{"time":8,"mag":2.04,"place":"7 km W of Cobb, California","lat":38.8245,"long":-122.804,"depth":3.2},{"time":23,"mag":2.35,"place":"7 km W of Cobb, California","lat":38.8131667,"long":-122.812,"depth":3.91},{"time":20,"mag":2.51,"place":"8 km WSW of Cobb, California","lat":38.8058333,"long":-122.8156667,"depth":2.47},{"time":15,"mag":2.46,"place":"8 km N of Dos Palos Y, California","lat":37.1266667,"long":-120.6338333,"depth":1.555},{"time":12,"mag":2.07,"place":"5 km WSW of Cobb, California","lat":38.7931667,"long":-122.7803333,"depth":1.471},{"time":4,"mag":2.49,"place":"7 km WSW of Cobb, California","lat":38.803,"long":-122.8075,"depth":2.02},{"time":3,"mag":2.01,"place":"7 km W of Cobb, California","lat":38.8141667,"long":-122.8125,"depth":2.99},{"time":17,"mag":2.44,"place":"3 km N of Cloverdale, California","lat":38.8358333,"long":-123.0115,"depth":5.33},{"time":15,"mag":2.65,"place":"28 km ESE of Tres Pinos, California","lat":36.6905,"long":-121.0236667,"depth":15.012},{"time":21,"mag":2.85,"place":"7 km WSW of Cobb, California","lat":38.8026667,"long":-122.8041667,"depth":2.841},{"time":7,"mag":2.46,"place":"6 km W of Cobb, California","lat":38.8223333,"long":-122.794,"depth":3.49},{"time":6,"mag":2.2,"place":"4 km ESE of Livermore, California","lat":37.6628333,"long":-121.72,"depth":4.671},{"time":9,"mag":2.39,"place":"7 km W of Cobb, California","lat":38.8176667,"long":-122.8066667,"depth":3.77},{"time":1,"mag":2.04,"place":"7 km W of Cobb, California","lat":38.8113333,"long":-122.8041667,"depth":2.5},{"time":6,"mag":2.43,"place":"6 km SSW of Cobb, California","lat":38.7678333,"long":-122.7403333,"depth":0.921},{"time":16,"mag":2.03,"place":"7 km WSW of Cobb, California","lat":38.8043333,"long":-122.8043333,"depth":1.99},{"time":16,"mag":2.41,"place":"8 km WSW of Cobb, California","lat":38.7998333,"long":-122.815,"depth":3.428},{"time":5,"mag":2.38,"place":"8 km WSW of Cobb, California","lat":38.7981667,"long":-122.8125,"depth":3.528},{"time":21,"mag":2.5,"place":"10 km NW of Broadmoor, California","lat":37.7555,"long":-122.5655,"depth":7.273},{"time":12,"mag":2.83,"place":"4 km WSW of Cobb, California","lat":38.7973333,"long":-122.7708333,"depth":0.143},{"time":8,"mag":2.22,"place":"24 km NE of Greenfield, California","lat":36.4658333,"long":-121.0431667,"depth":6.834},{"time":3,"mag":2.33,"place":"2 km SSW of San Juan Bautista, California","lat":36.8226667,"long":-121.5498333,"depth":6.86},{"time":16,"mag":2.64,"place":"5 km SW of Cobb, California","lat":38.7855,"long":-122.7695,"depth":1.181},{"time":15,"mag":2.38,"place":"11 km SE of Gilroy, California","lat":36.9385,"long":-121.474,"depth":20.421},{"time":12,"mag":2.58,"place":"7 km W of Cobb, California","lat":38.8133333,"long":-122.8083333,"depth":3.73},{"time":14,"mag":2.69,"place":"2 km ENE of Sand City, California","lat":36.6315,"long":-121.8213333,"depth":3.378},{"time":3,"mag":2.02,"place":"5 km SSW of Cobb, California","lat":38.7826667,"long":-122.7565,"depth":0.681},{"time":3,"mag":2.08,"place":"15 km N of Morgan Hill, California","lat":37.2681667,"long":-121.6553333,"depth":2.047},{"time":2,"mag":2.09,"place":"2 km SSW of Cobb, California","lat":38.7965,"long":-122.7331667,"depth":1.488},{"time":23,"mag":2.51,"place":"9 km ENE of Gilroy, California","lat":37.0258333,"long":-121.4685,"depth":6.683},{"time":14,"mag":2.11,"place":"5 km SW of Cobb, California","lat":38.7853333,"long":-122.7711667,"depth":1.728},{"time":18,"mag":2.41,"place":"6 km E of East Foothills, California","lat":37.384,"long":-121.7413333,"depth":5.942},{"time":15,"mag":2.32,"place":"3 km S of Cobb, California","lat":38.7948333,"long":-122.7228333,"depth":4.918},{"time":6,"mag":2.01,"place":"36 km ENE of Greenfield, California","lat":36.4828333,"long":-120.89,"depth":9.538},{"time":5,"mag":2.06,"place":"3 km S of San Juan Bautista, California","lat":36.8116667,"long":-121.5343333,"depth":6.75},{"time":22,"mag":2.72,"place":"5 km SW of Cobb, California","lat":38.7921667,"long":-122.778,"depth":3.738},{"time":5,"mag":2.21,"place":"12 km ENE of Cloverdale, California","lat":38.8356667,"long":-122.8825,"depth":2.032},{"time":5,"mag":2.3,"place":"5 km SSW of Gilroy, California","lat":36.9591667,"long":-121.5811667,"depth":4.341},{"time":4,"mag":2.55,"place":"6 km W of Cobb, California","lat":38.8178333,"long":-122.803,"depth":2.218},{"time":17,"mag":2.04,"place":"4 km ESE of Aromas, California","lat":36.869,"long":-121.5983333,"depth":5.872},{"time":18,"mag":3.16,"place":"5 km SW of Cobb, California","lat":38.7928333,"long":-122.7766667,"depth":0.928},{"time":11,"mag":2.06,"place":"11 km ESE of Sunol, California","lat":37.5671667,"long":-121.7666667,"depth":5.652},{"time":1,"mag":2.29,"place":"21 km SSE of Tres Pinos, California","lat":36.618,"long":-121.2223333,"depth":4.623},{"time":20,"mag":2.32,"place":"7 km WSW of Cobb, California","lat":38.8025,"long":-122.8048333,"depth":0.468},{"time":6,"mag":2.1,"place":"5 km WSW of Cobb, California","lat":38.797,"long":-122.7838333,"depth":3.668},{"time":23,"mag":2.09,"place":"3 km SSW of Cobb, California","lat":38.7956667,"long":-122.737,"depth":0.838},{"time":11,"mag":2.07,"place":"5 km SW of Cobb, California","lat":38.7875,"long":-122.7738333,"depth":1.808},{"time":7,"mag":2.28,"place":"2 km ESE of Diablo, California","lat":37.829,"long":-121.9365,"depth":9.9},{"time":7,"mag":2.26,"place":"7 km WSW of Cobb, California","lat":38.799,"long":-122.8068333,"depth":1.698},{"time":18,"mag":2.41,"place":"6 km SW of Cobb, California","lat":38.7866667,"long":-122.7761667,"depth":1.778},{"time":4,"mag":2.38,"place":"25 km ENE of King City, California","lat":36.3305,"long":-120.887,"depth":9.352},{"time":5,"mag":2.03,"place":"21 km SSE of Tres Pinos, California","lat":36.6125,"long":-121.216,"depth":4.414},{"time":18,"mag":2.45,"place":"7 km W of Cobb, California","lat":38.8148333,"long":-122.8106667,"depth":3.359},{"time":16,"mag":2.2,"place":"7 km WSW of Cobb, California","lat":38.8038333,"long":-122.8021667,"depth":2.068},{"time":13,"mag":2.15,"place":"23 km E of Big Sur, California","lat":36.2835,"long":-121.5415,"depth":4.354},{"time":2,"mag":2.25,"place":"24 km ENE of Soledad, California","lat":36.4963333,"long":-121.0721667,"depth":2.954},{"time":3,"mag":2.11,"place":"7 km W of Cobb, California","lat":38.8123333,"long":-122.8038333,"depth":2.458},{"time":15,"mag":2.03,"place":"25 km NE of Soledad, California","lat":36.5585,"long":-121.0895,"depth":9.704},{"time":11,"mag":2.19,"place":"5 km WSW of Ridgemark, California","lat":36.7888333,"long":-121.4148333,"depth":9.595},{"time":10,"mag":2.01,"place":"7 km W of Cobb, California","lat":38.8176667,"long":-122.8075,"depth":3.598},{"time":1,"mag":2.11,"place":"5 km WSW of Ridgemark, California","lat":36.7903333,"long":-121.4268333,"depth":8.765},{"time":1,"mag":2.16,"place":"9 km W of Cobb, California","lat":38.8273333,"long":-122.8356667,"depth":0.779},{"time":1,"mag":2.91,"place":"7 km W of Cobb, California","lat":38.8086667,"long":-122.8128333,"depth":1.058},{"time":23,"mag":2.07,"place":"6 km W of Cobb, California","lat":38.8191667,"long":-122.8023333,"depth":3.098},{"time":23,"mag":2.49,"place":"6 km W of Cobb, California","lat":38.8205,"long":-122.8023333,"depth":3.368},{"time":17,"mag":2.1,"place":"4 km NE of Pittsburg, California","lat":38.0648333,"long":-121.8528333,"depth":16.541},{"time":22,"mag":3.12,"place":"5 km SW of Cobb, California","lat":38.7815,"long":-122.7618333,"depth":2.528},{"time":9,"mag":2.06,"place":"25 km ENE of Greenfield, California","lat":36.444,"long":-121.0045,"depth":1.313},{"time":0,"mag":2.24,"place":"2 km N of Moskowite Corner, California","lat":38.4676667,"long":-122.1936667,"depth":2.854},{"time":23,"mag":2.4,"place":"13 km N of Morgan Hill, California","lat":37.2523333,"long":-121.638,"depth":4.742},{"time":5,"mag":2.48,"place":"7 km WSW of Cobb, California","lat":38.8038333,"long":-122.807,"depth":2.218},{"time":9,"mag":2.17,"place":"15 km SSE of Tres Pinos, California","lat":36.653,"long":-121.2683333,"depth":2.889},{"time":7,"mag":2.36,"place":"Northern California","lat":38.8043333,"long":-122.8051667,"depth":2.488},{"time":4,"mag":2.8,"place":"10 km SW of Ridgemark, California","lat":36.7486667,"long":-121.4476667,"depth":7.369},{"time":4,"mag":2.01,"place":"10 km SW of Ridgemark, California","lat":36.7498333,"long":-121.4491667,"depth":7.469},{"time":1,"mag":2,"place":"16 km NNW of Moskowite Corner, California","lat":38.5828333,"long":-122.2496667,"depth":7.406},{"time":15,"mag":2.14,"place":"7 km SSW of Livermore, California","lat":37.617,"long":-121.7905,"depth":1.809},{"time":3,"mag":2.86,"place":"5 km SSW of Cobb, California","lat":38.775,"long":-122.7461667,"depth":2.848},{"time":1,"mag":2.03,"place":"9 km W of Cobb, California","lat":38.8216667,"long":-122.8326667,"depth":0.916},{"time":0,"mag":2.19,"place":"9 km W of Cobb, California","lat":38.8233333,"long":-122.8313333,"depth":0.909},{"time":21,"mag":2.38,"place":"1 km E of Pajaro, California","lat":36.906,"long":-121.7361667,"depth":9.885},{"time":20,"mag":2.05,"place":"6 km W of Cobb, California","lat":38.8258333,"long":-122.798,"depth":2.998},{"time":15,"mag":2.07,"place":"5 km WSW of Cobb, California","lat":38.7965,"long":-122.782,"depth":3.988},{"time":15,"mag":2.37,"place":"6 km WSW of Cobb, California","lat":38.7931667,"long":-122.7815,"depth":3.708},{"time":11,"mag":2.52,"place":"5 km SW of Cobb, California","lat":38.792,"long":-122.7751667,"depth":2.758},{"time":10,"mag":2.9,"place":"10 km S of Tres Pinos, California","lat":36.6921667,"long":-121.3216667,"depth":3.795},{"time":10,"mag":2.04,"place":"5 km W of Glen Ellen, California","lat":38.3633333,"long":-122.591,"depth":3.37},{"time":8,"mag":2.24,"place":"2 km SSW of Cobb, California","lat":38.7998333,"long":-122.7303333,"depth":2.338},{"time":0,"mag":2.15,"place":"7 km W of Cobb, California","lat":38.8156667,"long":-122.8121667,"depth":2.559},{"time":23,"mag":3.12,"place":"7 km W of Cobb, California","lat":38.8198333,"long":-122.8068333,"depth":4.409},{"time":22,"mag":2.35,"place":"17 km NE of Gilroy, California","lat":37.0968333,"long":-121.4026667,"depth":9.021},{"time":18,"mag":3.09,"place":"5 km SW of Cobb, California","lat":38.7911667,"long":-122.7738333,"depth":1.768},{"time":15,"mag":2.16,"place":"23 km NNE of San Lucas, California","lat":36.3026667,"long":-120.8785,"depth":5.302},{"time":3,"mag":2.17,"place":"23 km NE of King City, California","lat":36.337,"long":-120.9178333,"depth":7.932},{"time":10,"mag":2.38,"place":"7 km WSW of Cobb, California","lat":38.8063333,"long":-122.81,"depth":3.878},{"time":10,"mag":2.01,"place":"7 km WSW of Cobb, California","lat":38.8051667,"long":-122.811,"depth":3.718},{"time":13,"mag":2.08,"place":"5 km S of Moskowite Corner, California","lat":38.3921667,"long":-122.1866667,"depth":4.332},{"time":2,"mag":2,"place":"6 km W of Cobb, California","lat":38.819,"long":-122.8026667,"depth":3.608},{"time":22,"mag":2.14,"place":"8 km W of Cobb, California","lat":38.8341667,"long":-122.822,"depth":0.738},{"time":9,"mag":2.36,"place":"5 km SW of Cobb, California","lat":38.7843333,"long":-122.7565,"depth":0.588},{"time":3,"mag":2.28,"place":"12 km NNE of Angwin, California","lat":38.6713333,"long":-122.3795,"depth":7.399},{"time":15,"mag":2.95,"place":"10 km WNW of Cobb, California","lat":38.8516667,"long":-122.8423333,"depth":0.566},{"time":7,"mag":2.44,"place":"5 km WSW of Cobb, California","lat":38.8005,"long":-122.7816667,"depth":4.008},{"time":22,"mag":2,"place":"6 km WSW of Gilroy, California","lat":36.983,"long":-121.6361667,"depth":4.549},{"time":6,"mag":2.04,"place":"5 km ESE of Interlaken, California","lat":36.937,"long":-121.679,"depth":11.186},{"time":4,"mag":2,"place":"33 km SE of Big Sur, California","lat":36.0698333,"long":-121.5225,"depth":13.968},{"time":13,"mag":2.18,"place":"1 km ENE of San Juan Bautista, California","lat":36.8538333,"long":-121.52,"depth":7.844},{"time":10,"mag":2.4,"place":"2 km WSW of Hollister, California","lat":36.8381667,"long":-121.4293333,"depth":7.285},{"time":10,"mag":2.18,"place":"26 km SE of Tres Pinos, California","lat":36.6083333,"long":-121.1276667,"depth":7.332},{"time":0,"mag":2.17,"place":"3 km W of Portola Valley, California","lat":37.3798333,"long":-122.2703333,"depth":9.492},{"time":0,"mag":2.21,"place":"12 km ENE of Cloverdale, California","lat":38.8358333,"long":-122.8795,"depth":3.115},{"time":8,"mag":2.02,"place":"10 km S of Davenport, California","lat":36.9166667,"long":-122.1936667,"depth":6.892},{"time":1,"mag":2.24,"place":"2 km WSW of Portola Valley, California","lat":37.3781667,"long":-122.2678333,"depth":9.92},{"time":20,"mag":2.02,"place":"14 km E of Seven Trees, California","lat":37.3,"long":-121.674,"depth":5.601},{"time":5,"mag":2.11,"place":"12 km ENE of Cloverdale, California","lat":38.8358333,"long":-122.8821667,"depth":1.215},{"time":5,"mag":2.24,"place":"12 km ENE of Cloverdale, California","lat":38.8365,"long":-122.8818333,"depth":1.235},{"time":17,"mag":3.41,"place":"7 km W of Cobb, California","lat":38.8215,"long":-122.8043333,"depth":4.038},{"time":4,"mag":2.57,"place":"5 km SW of Gilroy, California","lat":36.9726667,"long":-121.6101667,"depth":5.869},{"time":9,"mag":2.4,"place":"6 km SSW of Sunol, California","lat":37.5376667,"long":-121.9125,"depth":9.368},{"time":22,"mag":2.4,"place":"2 km SSW of San Juan Bautista, California","lat":36.828,"long":-121.549,"depth":4.591},{"time":9,"mag":2.22,"place":"9 km SW of Ridgemark, California","lat":36.7538333,"long":-121.4425,"depth":5.715},{"time":5,"mag":2.73,"place":"2 km WSW of Portola Valley, California","lat":37.379,"long":-122.2635,"depth":9.36},{"time":2,"mag":2.92,"place":"2 km WSW of Portola Valley, California","lat":37.3781667,"long":-122.2653333,"depth":9.11},{"time":1,"mag":2.79,"place":"7 km NE of San Juan Bautista, California","lat":36.9,"long":-121.4801667,"depth":5.934},{"time":14,"mag":2.58,"place":"3 km WSW of Cobb, California","lat":38.8068333,"long":-122.7543333,"depth":0.508},{"time":12,"mag":2.05,"place":"26 km SE of Tres Pinos, California","lat":36.6106667,"long":-121.1278333,"depth":7.732},{"time":11,"mag":2.63,"place":"4 km NE of San Leandro, California","lat":37.7498333,"long":-122.116,"depth":10.719},{"time":8,"mag":2.38,"place":"4 km NE of San Leandro, California","lat":37.7463333,"long":-122.1163333,"depth":10.829},{"time":6,"mag":3.07,"place":"7 km WSW of Cobb, California","lat":38.8075,"long":-122.8043333,"depth":2.728},{"time":5,"mag":3.24,"place":"4 km NE of San Leandro, California","lat":37.7538333,"long":-122.1146667,"depth":11.409},{"time":0,"mag":2.61,"place":"6 km SSW of Sunol, California","lat":37.5385,"long":-121.9111667,"depth":9.558},{"time":6,"mag":2.45,"place":"16 km ESE of Tres Pinos, California","lat":36.7088333,"long":-121.169,"depth":7.795},{"time":12,"mag":2.21,"place":"7 km W of Cobb, California","lat":38.8213333,"long":-122.8081667,"depth":3.088},{"time":11,"mag":3.04,"place":"11 km S of Tres Pinos, California","lat":36.6901667,"long":-121.3176667,"depth":3.715},{"time":11,"mag":2.03,"place":"11 km S of Tres Pinos, California","lat":36.6898333,"long":-121.3181667,"depth":3.565},{"time":7,"mag":2.04,"place":"16 km SW of Los Banos, California","lat":36.9488333,"long":-120.9711667,"depth":0.852},{"time":2,"mag":2.38,"place":"5 km SW of Cobb, California","lat":38.784,"long":-122.7568333,"depth":0.478},{"time":21,"mag":2.84,"place":"6 km WSW of Cobb, California","lat":38.8065,"long":-122.7946667,"depth":3.858},{"time":13,"mag":2.48,"place":"15 km SSE of Tres Pinos, California","lat":36.6591667,"long":-121.2763333,"depth":4.557},{"time":13,"mag":2.56,"place":"7 km S of Davenport, California","lat":36.9468333,"long":-122.184,"depth":8.764},{"time":9,"mag":2.39,"place":"Northern California","lat":38.7713333,"long":-122.7325,"depth":1.301},{"time":23,"mag":2.68,"place":"21 km NE of Soledad, California","lat":36.5648333,"long":-121.154,"depth":2.364},{"time":5,"mag":2.71,"place":"12 km WSW of Byron, California","lat":37.8306667,"long":-121.7676667,"depth":18.348},{"time":0,"mag":2.2,"place":"8 km ESE of Black Point-Green Point, California","lat":38.0875,"long":-122.4285,"depth":8.71},{"time":17,"mag":2.01,"place":"15 km SSE of Tres Pinos, California","lat":36.6581667,"long":-121.2763333,"depth":4.649},{"time":13,"mag":3.09,"place":"6 km W of Cobb, California","lat":38.8251667,"long":-122.7958333,"depth":0},{"time":12,"mag":2.23,"place":"2 km WSW of Portola Valley, California","lat":37.3786667,"long":-122.2636667,"depth":9.4},{"time":8,"mag":2.35,"place":"2 km W of Portola Valley, California","lat":37.3798333,"long":-122.2663333,"depth":9.512},{"time":8,"mag":2.57,"place":"2 km W of Portola Valley, California","lat":37.3801667,"long":-122.2656667,"depth":9.632},{"time":8,"mag":2.47,"place":"7 km WSW of Cobb, California","lat":38.8008333,"long":-122.8071667,"depth":0.268},{"time":21,"mag":2.07,"place":"6 km W of Cobb, California","lat":38.8186667,"long":-122.8023333,"depth":2.453},{"time":22,"mag":2.29,"place":"8 km WSW of Cobb, California","lat":38.7998333,"long":-122.8131667,"depth":3.261},{"time":15,"mag":2.16,"place":"4 km WNW of Cobb, California","lat":38.8441667,"long":-122.7711667,"depth":1.494},{"time":12,"mag":2.33,"place":"17 km NNW of Cazadero, California","lat":38.6833333,"long":-123.1608333,"depth":4.403},{"time":7,"mag":2.25,"place":"6 km W of Cobb, California","lat":38.8255,"long":-122.7971667,"depth":2.833},{"time":4,"mag":3.22,"place":"Central California","lat":36.9386667,"long":-121.6841667,"depth":11.756},{"time":3,"mag":3.05,"place":"4 km ESE of Interlaken, California","lat":36.9391667,"long":-121.6835,"depth":11.706},{"time":0,"mag":2.26,"place":"4 km WNW of Cobb, California","lat":38.8403333,"long":-122.7703333,"depth":0.943},{"time":0,"mag":2.36,"place":"4 km WNW of Cobb, California","lat":38.8375,"long":-122.7733333,"depth":0.693},{"time":22,"mag":2.54,"place":"2 km W of San Juan Bautista, California","lat":36.8463333,"long":-121.5688333,"depth":4.921},{"time":22,"mag":2.61,"place":"Central California","lat":36.8436667,"long":-121.5723333,"depth":5.591},{"time":9,"mag":2.02,"place":"4 km SW of Cobb, California","lat":38.7928333,"long":-122.757,"depth":1.711},{"time":19,"mag":2.38,"place":"7 km W of Cobb, California","lat":38.8116667,"long":-122.8043333,"depth":1.51},{"time":11,"mag":2.91,"place":"5 km SW of Cobb, California","lat":38.793,"long":-122.7786667,"depth":1.021},{"time":5,"mag":2.34,"place":"5 km SSW of Cobb, California","lat":38.7745,"long":-122.7478333,"depth":0.641},{"time":18,"mag":2,"place":"3 km S of San Juan Bautista, California","lat":36.8161667,"long":-121.5358333,"depth":6.25},{"time":15,"mag":2.35,"place":"23 km NE of Greenfield, California","lat":36.4651667,"long":-121.0458333,"depth":6.754},{"time":13,"mag":2.03,"place":"28 km ESE of Tres Pinos, California","lat":36.7141667,"long":-121.0166667,"depth":6.902},{"time":10,"mag":2.37,"place":"7 km S of Cobb, California","lat":38.7545,"long":-122.731,"depth":1.531},{"time":16,"mag":2.36,"place":"28 km ESE of Tres Pinos, California","lat":36.7145,"long":-121.0126667,"depth":5.742},{"time":13,"mag":3.21,"place":"28 km ESE of Tres Pinos, California","lat":36.7166667,"long":-121.0106667,"depth":5.232},{"time":10,"mag":2.08,"place":"2 km N of Del Monte Forest, California","lat":36.6051667,"long":-121.9491667,"depth":13.429},{"time":23,"mag":2.38,"place":"23 km NE of King City, California","lat":36.3841667,"long":-120.9646667,"depth":6.371},{"time":14,"mag":2.19,"place":"21 km NE of Soledad, California","lat":36.5546667,"long":-121.151,"depth":6.374},{"time":2,"mag":2,"place":"25 km ENE of Greenfield, California","lat":36.4436667,"long":-121.0041667,"depth":7.859},{"time":21,"mag":3.19,"place":"5 km SW of Cobb, California","lat":38.7853333,"long":-122.7706667,"depth":1.541},{"time":21,"mag":2.11,"place":"6 km SW of Cobb, California","lat":38.7891667,"long":-122.7856667,"depth":3.261},{"time":17,"mag":2.58,"place":"7 km W of Cobb, California","lat":38.8085,"long":-122.8126667,"depth":0.31},{"time":16,"mag":2.61,"place":"5 km S of Cobb, California","lat":38.7688333,"long":-122.7301667,"depth":2.661},{"time":5,"mag":2.15,"place":"6 km SE of Tres Pinos, California","lat":36.7563333,"long":-121.2606667,"depth":9.466},{"time":9,"mag":2.78,"place":"4 km ESE of Interlaken, California","lat":36.9393333,"long":-121.6831667,"depth":11.466},{"time":9,"mag":2.05,"place":"Central California","lat":36.941,"long":-121.6821667,"depth":11.256},{"time":17,"mag":2.23,"place":"13 km SSW of Fairmead, California","lat":36.9708333,"long":-120.2733333,"depth":8.465},{"time":12,"mag":2.1,"place":"6 km ENE of San Juan Bautista, California","lat":36.8663333,"long":-121.473,"depth":6.144},{"time":18,"mag":2.03,"place":"18 km ENE of Gilroy, California","lat":37.0946667,"long":-121.3948333,"depth":11.038},{"time":8,"mag":2.16,"place":"6 km SW of Big Sur, California","lat":36.225,"long":-121.8543333,"depth":18.939},{"time":5,"mag":2.06,"place":"6 km WSW of Cobb, California","lat":38.8091667,"long":-122.8006667,"depth":1.12},{"time":14,"mag":2.44,"place":"7 km WSW of Cobb, California","lat":38.8081667,"long":-122.8123333,"depth":1.21},{"time":15,"mag":2.74,"place":"9 km W of El Nido, California","lat":37.1456667,"long":-120.5941667,"depth":4.418},{"time":10,"mag":2,"place":"7 km W of Cobb, California","lat":38.822,"long":-122.8051667,"depth":3.343},{"time":13,"mag":2.01,"place":"3 km E of Aromas, California","lat":36.893,"long":-121.6083333,"depth":1.745},{"time":21,"mag":3.04,"place":"6 km WNW of Cobb, California","lat":38.8486667,"long":-122.7923333,"depth":1.628},{"time":16,"mag":2.63,"place":"Northern California","lat":38.7736667,"long":-122.7426667,"depth":2.061},{"time":20,"mag":2.1,"place":"6 km S of Cobb, California","lat":38.7611667,"long":-122.7211667,"depth":1.361},{"time":16,"mag":2.2,"place":"9 km ESE of Hidden Valley Lake, California","lat":38.7713333,"long":-122.4535,"depth":6.353},{"time":20,"mag":2.58,"place":"8 km WSW of Cobb, California","lat":38.8,"long":-122.8126667,"depth":3.201},{"time":10,"mag":2.56,"place":"1 km SSW of Concord, California","lat":37.9655,"long":-122.0403333,"depth":10.858},{"time":0,"mag":2.02,"place":"14 km SSE of Tres Pinos, California","lat":36.6648333,"long":-121.2805,"depth":3.947},{"time":22,"mag":2.37,"place":"Northern California","lat":38.774,"long":-122.7521667,"depth":0.251},{"time":21,"mag":2.08,"place":"6 km W of Middletown, California","lat":38.7595,"long":-122.692,"depth":1.028},{"time":13,"mag":2.56,"place":"17 km ENE of San Martin, California","lat":37.1195,"long":-121.4128333,"depth":25.236},{"time":12,"mag":2.49,"place":"22 km NE of Soledad, California","lat":36.5865,"long":-121.182,"depth":3.576},{"time":18,"mag":2.06,"place":"17 km SSE of Tres Pinos, California","lat":36.6461667,"long":-121.2535,"depth":3.44},{"time":9,"mag":2.68,"place":"4 km S of Cobb, California","lat":38.7806667,"long":-122.7233333,"depth":1.684},{"time":15,"mag":2.2,"place":"17 km ENE of Gilroy, California","lat":37.0893333,"long":-121.3963333,"depth":3.991},{"time":18,"mag":2.93,"place":"12 km ENE of Cloverdale, California","lat":38.8375,"long":-122.8816667,"depth":1.885},{"time":18,"mag":3.15,"place":"6 km SW of Cobb, California","lat":38.7831667,"long":-122.781,"depth":2.201},{"time":5,"mag":2.25,"place":"4 km SW of Cobb, California","lat":38.7893333,"long":-122.7575,"depth":1.471},{"time":3,"mag":3.39,"place":"4 km WSW of Cobb, California","lat":38.808,"long":-122.7686667,"depth":2.313},{"time":22,"mag":2.09,"place":"6 km WSW of Cobb, California","lat":38.8078333,"long":-122.8015,"depth":3.051},{"time":20,"mag":2.12,"place":"21 km NE of Soledad, California","lat":36.5496667,"long":-121.1426667,"depth":5.726},{"time":13,"mag":3.26,"place":"4 km WSW of Cobb, California","lat":38.7998333,"long":-122.7688333,"depth":1.483},{"time":12,"mag":2.2,"place":"19 km ENE of San Martin, California","lat":37.1278333,"long":-121.3996667,"depth":17.866},{"time":10,"mag":2.43,"place":"16 km E of Tres Pinos, California","lat":36.8008333,"long":-121.136,"depth":4.658},{"time":9,"mag":2.4,"place":"21 km NE of Soledad, California","lat":36.5506667,"long":-121.1426667,"depth":6.346},{"time":14,"mag":2.7,"place":"17 km ENE of Gilroy, California","lat":37.0886667,"long":-121.3966667,"depth":5.78},{"time":20,"mag":2.07,"place":"5 km SSW of Cobb, California","lat":38.775,"long":-122.7475,"depth":2.151},{"time":13,"mag":2.22,"place":"7 km WNW of Cobb, California","lat":38.84,"long":-122.8045,"depth":1.24},{"time":19,"mag":2.12,"place":"6 km W of Cobb, California","lat":38.8125,"long":-122.8,"depth":2.863},{"time":1,"mag":2.12,"place":"Northern California","lat":38.5275,"long":-122.3008333,"depth":3.706},{"time":22,"mag":2.22,"place":"7 km WSW of Cobb, California","lat":38.799,"long":-122.8005,"depth":1.661},{"time":21,"mag":2.01,"place":"12 km SW of Fairmead, California","lat":36.9935,"long":-120.2916667,"depth":5.523},{"time":9,"mag":3.22,"place":"2 km SSW of Cobb, California","lat":38.7983333,"long":-122.7315,"depth":2.644},{"time":0,"mag":2.53,"place":"17 km SSE of Tres Pinos, California","lat":36.6445,"long":-121.2601667,"depth":5.4},{"time":0,"mag":2.06,"place":"9 km SSW of Fairmead, California","lat":36.9963333,"long":-120.2383333,"depth":11.906},{"time":22,"mag":2.46,"place":"17 km SSE of Tres Pinos, California","lat":36.6443333,"long":-121.2596667,"depth":5.11},{"time":8,"mag":2.11,"place":"8 km ENE of Gilroy, California","lat":37.0376667,"long":-121.4856667,"depth":8.12},{"time":0,"mag":2.64,"place":"7 km ENE of Gilroy, California","lat":37.0346667,"long":-121.486,"depth":8.498},{"time":22,"mag":3.02,"place":"7 km ENE of Gilroy, California","lat":37.0365,"long":-121.488,"depth":8.66},{"time":18,"mag":2.21,"place":"3 km NW of Cloverdale, California","lat":38.8246667,"long":-123.043,"depth":14.137},{"time":7,"mag":2.05,"place":"5 km SSW of Cobb, California","lat":38.7805,"long":-122.7506667,"depth":4.051},{"time":17,"mag":2.5,"place":"8 km WSW of Cobb, California","lat":38.8078333,"long":-122.8135,"depth":0.753},{"time":5,"mag":2.03,"place":"25 km ENE of Greenfield, California","lat":36.4393333,"long":-120.998,"depth":2.039},{"time":1,"mag":2.41,"place":"8 km W of Cobb, California","lat":38.8085,"long":-122.8145,"depth":3.55},{"time":19,"mag":2.41,"place":"3 km NNE of San Leandro, California","lat":37.7551667,"long":-122.1423333,"depth":4.061},{"time":18,"mag":2.17,"place":"10 km W of Cobb, California","lat":38.8175,"long":-122.846,"depth":1.289},{"time":8,"mag":2.55,"place":"Northern California","lat":38.1033333,"long":-122.0985,"depth":5.726},{"time":10,"mag":2.25,"place":"6 km NE of Ridgemark, California","lat":36.8503333,"long":-121.3141667,"depth":5.664},{"time":18,"mag":2.11,"place":"5 km SW of Cobb, California","lat":38.7903333,"long":-122.7783333,"depth":1.281},{"time":15,"mag":2.02,"place":"12 km ENE of Cloverdale, California","lat":38.8345,"long":-122.8823333,"depth":2.395},{"time":11,"mag":2.16,"place":"2 km SSW of Cobb, California","lat":38.7995,"long":-122.7345,"depth":1.974},{"time":6,"mag":3.14,"place":"7 km WSW of Cobb, California","lat":38.7968333,"long":-122.7973333,"depth":0.741},{"time":5,"mag":2.24,"place":"7 km WSW of Cobb, California","lat":38.7975,"long":-122.8053333,"depth":2.388},{"time":21,"mag":2.07,"place":"8 km NNW of Hollister, California","lat":36.9206667,"long":-121.4558333,"depth":8.933},{"time":16,"mag":2.67,"place":"3 km ESE of Aromas, California","lat":36.8798333,"long":-121.6085,"depth":5.016},{"time":16,"mag":2.03,"place":"5 km W of Cobb, California","lat":38.8163333,"long":-122.7891667,"depth":0.29},{"time":5,"mag":2.12,"place":"8 km WNW of Cobb, California","lat":38.8405,"long":-122.8133333,"depth":0.38},{"time":2,"mag":2.58,"place":"3 km ESE of Piedmont, California","lat":37.8115,"long":-122.1923333,"depth":4.313},{"time":17,"mag":2.17,"place":"18 km ENE of Gilroy, California","lat":37.0946667,"long":-121.395,"depth":6.463},{"time":12,"mag":2.07,"place":"16 km ENE of Gilroy, California","lat":37.0696667,"long":-121.4038333,"depth":6.426},{"time":10,"mag":2.77,"place":"2 km SSW of Cobb, California","lat":38.7963333,"long":-122.7328333,"depth":1.744},{"time":22,"mag":2.18,"place":"1 km SSW of Hollister, California","lat":36.838,"long":-121.4105,"depth":8.105},{"time":17,"mag":2.02,"place":"9 km SW of Ridgemark, California","lat":36.7486667,"long":-121.4363333,"depth":6.129},{"time":13,"mag":2.71,"place":"12 km E of Gilroy, California","lat":37.013,"long":-121.4253333,"depth":13.073},{"time":13,"mag":2.41,"place":"18 km ENE of Gilroy, California","lat":37.0958333,"long":-121.3958333,"depth":24.075},{"time":13,"mag":2.22,"place":"8 km SSW of Tres Pinos, California","lat":36.7221667,"long":-121.3636667,"depth":2.859},{"time":11,"mag":2.29,"place":"2 km SSW of Cobb, California","lat":38.7991667,"long":-122.7318333,"depth":2.051},{"time":1,"mag":2.18,"place":"14 km N of Morgan Hill, California","lat":37.2635,"long":-121.6478333,"depth":3.237},{"time":9,"mag":2.3,"place":"7 km W of Cobb, California","lat":38.8158333,"long":-122.8038333,"depth":2.82},{"time":3,"mag":2.12,"place":"9 km ESE of East Foothills, California","lat":37.3558333,"long":-121.7173333,"depth":7.588},{"time":13,"mag":2.4,"place":"2 km NNW of Aromas, California","lat":36.9085,"long":-121.655,"depth":10.861},{"time":9,"mag":2.18,"place":"3 km SSW of Cobb, California","lat":38.7921667,"long":-122.7438333,"depth":1.504},{"time":21,"mag":2.05,"place":"10 km ESE of East Foothills, California","lat":37.3451667,"long":-121.7086667,"depth":7.358},{"time":21,"mag":2.04,"place":"10 km ESE of East Foothills, California","lat":37.3448333,"long":-121.7091667,"depth":7.428},{"time":21,"mag":2.56,"place":"Northern California","lat":37.3428333,"long":-121.7073333,"depth":7.478},{"time":20,"mag":2.01,"place":"6 km SW of Cobb, California","lat":38.7845,"long":-122.774,"depth":0.811},{"time":9,"mag":2.28,"place":"9 km NNE of Morgan Hill, California","lat":37.201,"long":-121.5968333,"depth":5.653},{"time":12,"mag":2.9,"place":"7 km W of Cobb, California","lat":38.8246667,"long":-122.8068333,"depth":0.99},{"time":13,"mag":2.06,"place":"2 km SSW of Cobb, California","lat":38.798,"long":-122.7385,"depth":1.614},{"time":21,"mag":2.03,"place":"2 km SSW of Cobb, California","lat":38.7986667,"long":-122.7325,"depth":2.084},{"time":21,"mag":2.27,"place":"18 km ENE of Gilroy, California","lat":37.0926667,"long":-121.3925,"depth":14.762},{"time":8,"mag":2.14,"place":"5 km SSW of Cobb, California","lat":38.7755,"long":-122.7471667,"depth":2.051},{"time":18,"mag":2.61,"place":"14 km E of Angwin, California","lat":38.553,"long":-122.2883333,"depth":3.276},{"time":16,"mag":2.15,"place":"20 km SSE of Tres Pinos, California","lat":36.6225,"long":-121.2325,"depth":5.43},{"time":14,"mag":2.92,"place":"5 km NNW of Grayson, California","lat":37.6068333,"long":-121.2041667,"depth":25.56},{"time":23,"mag":2.19,"place":"4 km WSW of Cobb, California","lat":38.81,"long":-122.7733333,"depth":1.613},{"time":8,"mag":2.52,"place":"6 km WSW of Cobb, California","lat":38.809,"long":-122.7976667,"depth":1.16},{"time":23,"mag":2.58,"place":"42 km ESE of Tres Pinos, California","lat":36.6085,"long":-120.9038333,"depth":5.211},{"time":13,"mag":2.14,"place":"Central California","lat":36.6385,"long":-121.2388333,"depth":7.76},{"time":6,"mag":2.15,"place":"13 km NW of Lockwood, California","lat":36.044,"long":-121.1666667,"depth":13.93},{"time":19,"mag":3.08,"place":"22 km NE of San Lucas, California","lat":36.2503333,"long":-120.8151667,"depth":5.876}]